[
    {
        "numero_unite": 4,
        "numero_automate": 1,
        "type_automate": "0X0000BA20",
        "temperature_cuve": 2.6,
        "temperature_exterieur": 11.9,
        "poids_lait_cuve": 4106,
        "poids_produit_fini": 399,
        "pH": 6.9,
        "K": 40,
        "NaCl": 1.5,
        "salmonelle": 30,
        "Ecoli": 40,
        "listeria": 38,
        "dateheure": "29-05-2020 09:21:08"
    },
    {
        "numero_unite": 4,
        "numero_automate": 2,
        "type_automate": "0X0000BA2F",
        "temperature_cuve": 2.6,
        "temperature_exterieur": 11.6,
        "poids_lait_cuve": 3981,
        "poids_produit_fini": 29,
        "pH": 6.9,
        "K": 41,
        "NaCl": 1.6,
        "salmonelle": 31,
        "Ecoli": 35,
        "listeria": 39,
        "dateheure": "29-05-2020 09:21:08"
    },
    {
        "numero_unite": 4,
        "numero_automate": 3,
        "type_automate": "0X0000BA20",
        "temperature_cuve": 3.1,
        "temperature_exterieur": 9.7,
        "poids_lait_cuve": 4105,
        "poids_produit_fini": 299,
        "pH": 7.0,
        "K": 38,
        "NaCl": 1.2,
        "salmonelle": 27,
        "Ecoli": 38,
        "listeria": 52,
        "dateheure": "29-05-2020 09:21:08"
    },
    {
        "numero_unite": 4,
        "numero_automate": 4,
        "type_automate": "0X0000BA2F",
        "temperature_cuve": 3.0,
        "temperature_exterieur": 9.5,
        "poids_lait_cuve": 3514,
        "poids_produit_fini": 452,
        "pH": 7.0,
        "K": 39,
        "NaCl": 1.6,
        "salmonelle": 28,
        "Ecoli": 35,
        "listeria": 54,
        "dateheure": "29-05-2020 09:21:08"
    },
    {
        "numero_unite": 4,
        "numero_automate": 5,
        "type_automate": "0X0000BA20",
        "temperature_cuve": 4.0,
        "temperature_exterieur": 9.5,
        "poids_lait_cuve": 4034,
        "poids_produit_fini": 978,
        "pH": 7.0,
        "K": 47,
        "NaCl": 1.7,
        "salmonelle": 17,
        "Ecoli": 37,
        "listeria": 43,
        "dateheure": "29-05-2020 09:21:08"
    },
    {
        "numero_unite": 4,
        "numero_automate": 6,
        "type_automate": "0X0000BA2F",
        "temperature_cuve": 2.6,
        "temperature_exterieur": 11.1,
        "poids_lait_cuve": 3768,
        "poids_produit_fini": 323,
        "pH": 6.9,
        "K": 47,
        "NaCl": 1.1,
        "salmonelle": 31,
        "Ecoli": 39,
        "listeria": 44,
        "dateheure": "29-05-2020 09:21:08"
    },
    {
        "numero_unite": 4,
        "numero_automate": 7,
        "type_automate": "0X0000BA20",
        "temperature_cuve": 3.3,
        "temperature_exterieur": 11.4,
        "poids_lait_cuve": 4500,
        "poids_produit_fini": 398,
        "pH": 6.9,
        "K": 35,
        "NaCl": 1.3,
        "salmonelle": 35,
        "Ecoli": 49,
        "listeria": 31,
        "dateheure": "29-05-2020 09:21:08"
    },
    {
        "numero_unite": 4,
        "numero_automate": 8,
        "type_automate": "0X0000BA2F",
        "temperature_cuve": 3.9,
        "temperature_exterieur": 8.6,
        "poids_lait_cuve": 4263,
        "poids_produit_fini": 199,
        "pH": 7.1,
        "K": 45,
        "NaCl": 1.3,
        "salmonelle": 18,
        "Ecoli": 35,
        "listeria": 28,
        "dateheure": "29-05-2020 09:21:08"
    },
    {
        "numero_unite": 4,
        "numero_automate": 9,
        "type_automate": "0X0000BA20",
        "temperature_cuve": 2.7,
        "temperature_exterieur": 9.4,
        "poids_lait_cuve": 4024,
        "poids_produit_fini": 590,
        "pH": 7.0,
        "K": 47,
        "NaCl": 1.4,
        "salmonelle": 26,
        "Ecoli": 46,
        "listeria": 52,
        "dateheure": "29-05-2020 09:21:08"
    },
    {
        "numero_unite": 4,
        "numero_automate": 10,
        "type_automate": "0X0000BA2F",
        "temperature_cuve": 3.4,
        "temperature_exterieur": 13.6,
        "poids_lait_cuve": 4018,
        "poids_produit_fini": 962,
        "pH": 7.1,
        "K": 46,
        "NaCl": 1.5,
        "salmonelle": 20,
        "Ecoli": 38,
        "listeria": 44,
        "dateheure": "29-05-2020 09:21:08"
    }
]